powerline_inject/__init__.py
powerline_inject-0.1.6.dist-info/LICENSE
powerline_inject-0.1.6.dist-info/METADATA
powerline_inject-0.1.6.dist-info/WHEEL
powerline_inject-0.1.6.dist-info/entry_points.txt
powerline_inject-0.1.6.dist-info/top_level.txt
powerline_inject-0.1.6.dist-info/RECORD
